jps_effort_tracker_utils/__init__.py
jps_effort_tracker_utils/cli.py
jps_effort_tracker_utils/constants.py
jps_effort_tracker_utils/manager.py
jps_effort_tracker_utils/conf/config.yaml
jps_effort_tracker_utils-1.2.0.dist-info/METADATA
jps_effort_tracker_utils-1.2.0.dist-info/WHEEL
jps_effort_tracker_utils-1.2.0.dist-info/entry_points.txt
jps_effort_tracker_utils-1.2.0.dist-info/top_level.txt
jps_effort_tracker_utils-1.2.0.dist-info/RECORD
