Metadata-Version: 2.4
Name: jps-effort-tracker-utils
Version: 1.2.0
Summary: A command-line task and effort tracking utility for managing daily tasks with priorities, effort estimates, and status tracking.
Author-email: Jaideep Sundaram <jai.python3@gmail.com>
Project-URL: Homepage, https://github.com/jai-python3/effort-tracker-utils
Project-URL: Repository, https://github.com/jai-python3/effort-tracker-utils
Project-URL: Issues, https://github.com/jai-python3/effort-tracker-utils/issues
Keywords: jps_effort_tracker_utils
Classifier: Development Status :: 2 - Pre-Alpha
Classifier: Intended Audience :: Developers
Classifier: Natural Language :: English
Classifier: Programming Language :: Python :: 3
Classifier: Programming Language :: Python :: 3.12
Requires-Python: >=3.12
Requires-Dist: typer>=0.12.0
Requires-Dist: colorama
Requires-Dist: Pydantic
Requires-Dist: PyYAML
Requires-Dist: Rich
Provides-Extra: dev
Requires-Dist: pytest>=8.0.0; extra == "dev"
Requires-Dist: pytest-cov>=5.0.0; extra == "dev"
Requires-Dist: coverage>=4.5.4; extra == "dev"
Requires-Dist: tox>=3.14.0; extra == "dev"
Requires-Dist: black; extra == "dev"
Requires-Dist: deadcode; extra == "dev"
Requires-Dist: flake8; extra == "dev"
Requires-Dist: isort; extra == "dev"
Requires-Dist: mypy; extra == "dev"
Requires-Dist: pre-commit; extra == "dev"
Requires-Dist: pydocstyle; extra == "dev"
Requires-Dist: pylint; extra == "dev"
Requires-Dist: rm_unneeded_f_str; extra == "dev"
Requires-Dist: vulture; extra == "dev"
Requires-Dist: bump-my-version>=1.0.1; extra == "dev"
Requires-Dist: wheel; extra == "dev"
Requires-Dist: watchdog; extra == "dev"
Requires-Dist: Sphinx; extra == "dev"
Requires-Dist: twine; extra == "dev"
Requires-Dist: git-changelog>=2.0.0; extra == "dev"
